LICENSE
README.md
setup.py
semarl/__init__.py
semarl/main.py
semarl.egg-info/PKG-INFO
semarl.egg-info/SOURCES.txt
semarl.egg-info/dependency_links.txt
semarl.egg-info/entry_points.txt
semarl.egg-info/requires.txt
semarl.egg-info/top_level.txt