Metadata-Version: 2.1
Name: semarl
Version: 0.1.1
Summary: Magically turns your semantic git logs to release summary, helpful for release maintainers.
Home-page: https://github.com/HanzHaxors/ReleaseSummaryGenerator
Author: Hanz
Author-email: hanz@godot.id
Classifier: Development Status :: 4 - Beta
Classifier: Environment :: Console
Classifier: Intended Audience :: Developers
Classifier: License :: OSI Approved :: The Unlicense (Unlicense)
Classifier: Topic :: Documentation
Classifier: Topic :: Software Development :: Libraries :: Python Modules
Classifier: Topic :: Software Development :: Version Control :: Git
Requires-Python: >=3.6
License-File: LICENSE
